{"saved_itinerary":[{"id":"1","steps":"Colonna di Marco Aurelio\/Monumento a Goethe\/Pantheon\/Monumento a José Gervasio Artigas\/Statue dei Dioscuri\/Monumento a Quintino Sella","username":"aq"},{"id":"2","steps":"Cordonata Capitolina\/Piazza di San Silvestro\/Fontana della Dea Roma\/Scalinata di Trinità dei MontiFontana della Dea Roma\/Sacrario delle Bandiere delle Forze Armate","username":"aq"},{"id":"3","steps":"addd-","username":"sw"},{"id":"4","steps":"colo-","username":"sw"},{"id":"5","steps":"colosseo-","username":"sw"},{"id":"6","steps":"colosseo-","username":"sw"},{"id":"7","steps":"colosseo-","username":"sw"},{"id":"1","steps":"coslo-","username":"sw"},{"id":"1","steps":"coslo-","username":"sw"},{"id":"1","steps":"coslo-","username":"sw"},{"id":"1","steps":"colosseo-","username":"sw"},{"id":"1","steps":"colosseo-","username":"sw"},{"id":"1","steps":"colosseo-","username":"aq"},{"id":"1","steps":"colosseo-","username":"aq"}]}